sudachi_b_imitator/__init__.py
sudachi_b_imitator/config.json
sudachi_b_imitator/ma_imitator.py
sudachi_b_imitator/model.onnx
sudachi_b_imitator-0.2.1.dist-info/LICENSE
sudachi_b_imitator-0.2.1.dist-info/METADATA
sudachi_b_imitator-0.2.1.dist-info/WHEEL
sudachi_b_imitator-0.2.1.dist-info/top_level.txt
sudachi_b_imitator-0.2.1.dist-info/RECORD
